Metadata-Version: 1.0
Name: Damola-distributions
Version: 1.0
Summary: Gaussian and Binomial distributions
Home-page: UNKNOWN
Author: UNKNOWN
Author-email: damolaoriola@gmail.com
License: UNKNOWN
Platform: UNKNOWN
